SanicApiKey/__init__.py
SanicApiKey-1.0.1.dist-info/METADATA
SanicApiKey-1.0.1.dist-info/WHEEL
SanicApiKey-1.0.1.dist-info/top_level.txt
SanicApiKey-1.0.1.dist-info/RECORD
