Metadata-Version: 2.1
Name: SanicApiKey
Version: 1.0.1
Summary: Basic Sanic API Key plugin.
Home-page: https://github.com/quiec/SanicApiKey
Author: Yusuf Usta
Author-email: yusuf@fusuf.codes
Maintainer: Yusuf Usta
Maintainer-email: yusuf@fusuf.codes
License: GPL3
Keywords: sanic
Platform: UNKNOWN
Classifier: Intended Audience :: Developers
Classifier: License :: OSI Approved :: GNU General Public License v3 (GPLv3)
Classifier: Programming Language :: Python :: 3.6
Classifier: Programming Language :: Python :: 3.7
Classifier: Programming Language :: Python :: 3.8
Classifier: Programming Language :: Python :: 3.9
Requires-Dist: sanic
